aiida_optimize/__init__.py
aiida_optimize/_optimization_workchain.py
aiida_optimize/_utils.py
aiida_optimize/helpers.py
aiida_optimize/process_inputs.py
aiida_optimize/py.typed
aiida_optimize/engines/__init__.py
aiida_optimize/engines/_bisection.py
aiida_optimize/engines/_convergence.py
aiida_optimize/engines/_nelder_mead.py
aiida_optimize/engines/_parameter_sweep.py
aiida_optimize/engines/_particle_swarm.py
aiida_optimize/engines/_result_mapping.py
aiida_optimize/engines/base.py
aiida_optimize/wrappers/__init__.py
aiida_optimize/wrappers/_add_inputs.py
aiida_optimize/wrappers/_concatenate.py
aiida_optimize/wrappers/_create_evaluate.py
aiida_optimize/wrappers/_run_or_submit.py
aiida_optimize-1.0.2.dist-info/LICENSE.txt
aiida_optimize-1.0.2.dist-info/METADATA
aiida_optimize-1.0.2.dist-info/WHEEL
aiida_optimize-1.0.2.dist-info/entry_points.txt
aiida_optimize-1.0.2.dist-info/top_level.txt
aiida_optimize-1.0.2.dist-info/RECORD
